[
    {
        "action": "press_and_hold_start_stop_button",
        "bbox_label": [
            "1_start"
        ],
        "action_type": "press_and_hold_button",
        "bboxes": [
            {
                "image_name": "1_0",
                "bbox": [
                    [
                        0.7083333333333334,
                        0.6813725490196079,
                        0.8815359477124183,
                        0.7432598039215687
                    ]
                ]
            }
        ]
    },
    {
        "action": "press_minus_button",
        "bbox_label": [
            "1_minus"
        ],
        "action_type": "press_button",
        "bboxes": [
            {
                "image_name": "1_0",
                "bbox": [
                    [
                        0.5106209150326797,
                        0.7928921568627451,
                        0.6339869281045751,
                        0.8486519607843137
                    ]
                ]
            }
        ]
    },
    {
        "action": "press_start_stop_button",
        "bbox_label": [
            "1_start"
        ],
        "action_type": "press_button",
        "bboxes": [
            {
                "image_name": "1_0",
                "bbox": [
                    [
                        0.7083333333333334,
                        0.6813725490196079,
                        0.8815359477124183,
                        0.7432598039215687
                    ]
                ]
            }
        ]
    },
    {
        "action": "press_plus_button",
        "bbox_label": [
            "1_plus"
        ],
        "action_type": "press_button",
        "bboxes": [
            {
                "image_name": "1_0",
                "bbox": [
                    [
                        0.29901960784313725,
                        0.7971813725490197,
                        0.44199346405228757,
                        0.8529411764705882
                    ]
                ]
            }
        ]
    },
    {
        "action": "press_loaf_button",
        "bbox_label": [
            "1_loaf"
        ],
        "action_type": "press_button",
        "bboxes": [
            {
                "image_name": "1_0",
                "bbox": [
                    [
                        0.7197712418300654,
                        0.7702205882352942,
                        0.9011437908496732,
                        0.8235294117647058
                    ]
                ]
            }
        ]
    },
    {
        "action": "press_color_button",
        "bbox_label": [
            "1_color"
        ],
        "action_type": "press_button",
        "bboxes": [
            {
                "image_name": "1_0",
                "bbox": [
                    [
                        0.0457516339869281,
                        0.7781862745098039,
                        0.22140522875816993,
                        0.8425245098039216
                    ]
                ]
            }
        ]
    },
    {
        "action": "press_menu_button",
        "bbox_label": [
            "1_menu"
        ],
        "action_type": "press_button",
        "bboxes": [
            {
                "image_name": "1_0",
                "bbox": [
                    [
                        0.051470588235294115,
                        0.6856617647058824,
                        0.2246732026143791,
                        0.7518382352941176
                    ]
                ]
            }
        ]
    }
]