[
    {
        "action": "press_program_buttons",
        "bbox_label": [
            "3_program"
        ],
        "action_type": "press_button",
        "bboxes": [
            {
                "image_name": "5_0",
                "bbox": [
                    [
                        0.5555555555555556,
                        0.8273809523809523,
                        0.5992063492063492,
                        0.8611111111111112
                    ]
                ]
            }
        ]
    },
    {
        "action": "press_on_off_button",
        "bbox_label": [
            "3_on_off"
        ],
        "action_type": "press_button",
        "bboxes": [
            {
                "image_name": "5_0",
                "bbox": [
                    [
                        0.791005291005291,
                        0.7668650793650794,
                        0.8386243386243386,
                        0.7986111111111112
                    ]
                ]
            }
        ]
    },
    {
        "action": "press_rinse_button",
        "bbox_label": [
            "3_rinse"
        ],
        "action_type": "press_button",
        "bboxes": [
            {
                "image_name": "5_0",
                "bbox": [
                    [
                        0.43386243386243384,
                        0.8323412698412699,
                        0.4775132275132275,
                        0.8660714285714286
                    ]
                ]
            }
        ]
    },
    {
        "action": "press_spin_button",
        "bbox_label": [
            "3_spin"
        ],
        "action_type": "press_button",
        "bboxes": [
            {
                "image_name": "5_0",
                "bbox": [
                    [
                        0.4894179894179894,
                        0.8313492063492064,
                        0.5357142857142857,
                        0.8630952380952381
                    ]
                ]
            }
        ]
    },
    {
        "action": "press_water_level_button",
        "bbox_label": [
            "3_water"
        ],
        "action_type": "press_button",
        "bboxes": [
            {
                "image_name": "5_0",
                "bbox": [
                    [
                        0.3187830687830688,
                        0.8353174603174603,
                        0.36243386243386244,
                        0.8680555555555556
                    ]
                ]
            }
        ]
    },
    {
        "action": "press_time_manager_button",
        "bbox_label": [
            "3_time"
        ],
        "action_type": "press_button",
        "bboxes": [
            {
                "image_name": "5_0",
                "bbox": [
                    [
                        0.37566137566137564,
                        0.8353174603174603,
                        0.42063492063492064,
                        0.8660714285714286
                    ]
                ]
            }
        ]
    },
    {
        "action": "press_clean_tub_off_button",
        "bbox_label": [
            "3_tub"
        ],
        "action_type": "press_button",
        "bboxes": [
            {
                "image_name": "5_0",
                "bbox": [
                    [
                        0.6243386243386243,
                        0.8283730158730159,
                        0.6653439153439153,
                        0.8611111111111112
                    ]
                ]
            }
        ]
    },
    {
        "action": "press_and_hold_water_level_button_and_time_manager_button",
        "bbox_label": [
            "3_water",
            "3_time"
        ],
        "action_type": "press_button",
        "duration": 3,
        "bboxes": [
            {
                "image_name": "5_0",
                "bbox": [
                    [
                        0.37566137566137564,
                        0.8353174603174603,
                        0.42063492063492064,
                        0.8660714285714286
                    ],
                    [
                        0.3187830687830688,
                        0.8353174603174603,
                        0.36243386243386244,
                        0.8680555555555556
                    ]
                ]
            }
        ]
    },
    {
        "action": "press_start_pause_button",
        "bbox_label": [
            "3_start"
        ],
        "action_type": "press_button",
        "bboxes": [
            {
                "image_name": "5_0",
                "bbox": [
                    [
                        0.7116402116402116,
                        0.7738095238095238,
                        0.7526455026455027,
                        0.8055555555555556
                    ]
                ]
            }
        ]
    }
]