[
    {
        "action": "turn_function_dial_anticlockwise",
        "bbox_label": [
            "2_function"
        ],
        "action_type": "turn_dial_anti_clockwise",
        "bboxes": [
            {
                "image_name": "2_0",
                "bbox": [
                    [
                        0.5465686274509803,
                        0.2604166666666667,
                        0.7712418300653595,
                        0.4252450980392157
                    ]
                ]
            }
        ]
    },
    {
        "action": "turn_function_dial_clockwise",
        "bbox_label": [
            "2_function"
        ],
        "action_type": "turn_dial_clockwise",
        "bboxes": [
            {
                "image_name": "2_0",
                "bbox": [
                    [
                        0.5465686274509803,
                        0.2604166666666667,
                        0.7712418300653595,
                        0.4252450980392157
                    ]
                ]
            }
        ]
    },
    {
        "action": "turn_timer_dial_anticlockwise",
        "bbox_label": [
            "2_timer"
        ],
        "action_type": "turn_dial_anti_clockwise",
        "bboxes": [
            {
                "image_name": "2_0",
                "bbox": [
                    [
                        0.5629084967320261,
                        0.6985294117647058,
                        0.8080065359477124,
                        0.8860294117647058
                    ]
                ]
            }
        ]
    },
    {
        "action": "turn_timer_dial_clockwise",
        "bbox_label": [
            "2_timer"
        ],
        "action_type": "turn_dial_clockwise",
        "bboxes": [
            {
                "image_name": "2_0",
                "bbox": [
                    [
                        0.5629084967320261,
                        0.6985294117647058,
                        0.8080065359477124,
                        0.8860294117647058
                    ]
                ]
            }
        ]
    },
    {
        "action": "turn_lower_element_temperature_dial_anticlockwise",
        "bbox_label": [
            "2_bottom"
        ],
        "action_type": "turn_dial_anti_clockwise",
        "bboxes": [
            {
                "image_name": "2_0",
                "bbox": [
                    [
                        0.553921568627451,
                        0.4803921568627451,
                        0.7875816993464052,
                        0.6537990196078431
                    ]
                ]
            }
        ]
    },
    {
        "action": "turn_lower_element_temperature_dial_clockwise",
        "bbox_label": [
            "2_bottom"
        ],
        "action_type": "turn_dial_clockwise",
        "bboxes": [
            {
                "image_name": "2_0",
                "bbox": [
                    [
                        0.553921568627451,
                        0.4803921568627451,
                        0.7875816993464052,
                        0.6537990196078431
                    ]
                ]
            }
        ]
    },
    {
        "action": "turn_upper_element_temperature_dial_anticlockwise",
        "bbox_label": [
            "2_upper"
        ],
        "action_type": "turn_dial_anti_clockwise",
        "bboxes": [
            {
                "image_name": "2_0",
                "bbox": [
                    [
                        0.5310457516339869,
                        0.031862745098039214,
                        0.7826797385620915,
                        0.20036764705882354
                    ]
                ]
            }
        ]
    },
    {
        "action": "turn_upper_element_temperature_dial_clockwise",
        "bbox_label": [
            "2_upper"
        ],
        "action_type": "turn_dial_clockwise",
        "bboxes": [
            {
                "image_name": "2_0",
                "bbox": [
                    [
                        0.5310457516339869,
                        0.031862745098039214,
                        0.7826797385620915,
                        0.20036764705882354
                    ]
                ]
            }
        ]
    }
]